pinaxai/__about__.py
pinaxai/__init__.py
pinaxai/constants.py
pinaxai/debug.py
pinaxai/exceptions.py
pinaxai/media.py
pinaxai/py.typed
pinaxai/agent/__init__.py
pinaxai/agent/agent.py
pinaxai/agent/metrics.py
pinaxai/api/__init__.py
pinaxai/api/agent.py
pinaxai/api/api.py
pinaxai/api/playground.py
pinaxai/api/routes.py
pinaxai/api/team.py
pinaxai/api/user.py
pinaxai/api/workspace.py
pinaxai/api/schemas/__init__.py
pinaxai/api/schemas/agent.py
pinaxai/api/schemas/playground.py
pinaxai/api/schemas/response.py
pinaxai/api/schemas/team.py
pinaxai/api/schemas/user.py
pinaxai/api/schemas/workspace.py
pinaxai/cli/__init__.py
pinaxai/cli/auth_server.py
pinaxai/cli/config.py
pinaxai/cli/console.py
pinaxai/cli/credentials.py
pinaxai/cli/entrypoint.py
pinaxai/cli/operator.py
pinaxai/cli/settings.py
pinaxai/cli/ws/__init__.py
pinaxai/cli/ws/ws_cli.py
pinaxai/document/__init__.py
pinaxai/document/base.py
pinaxai/document/chunking/__init__.py
pinaxai/document/chunking/agentic.py
pinaxai/document/chunking/document.py
pinaxai/document/chunking/fixed.py
pinaxai/document/chunking/recursive.py
pinaxai/document/chunking/semantic.py
pinaxai/document/chunking/strategy.py
pinaxai/document/reader/__init__.py
pinaxai/document/reader/arxiv_reader.py
pinaxai/document/reader/base.py
pinaxai/document/reader/csv_reader.py
pinaxai/document/reader/docx_reader.py
pinaxai/document/reader/firecrawl_reader.py
pinaxai/document/reader/json_reader.py
pinaxai/document/reader/pdf_reader.py
pinaxai/document/reader/text_reader.py
pinaxai/document/reader/url_reader.py
pinaxai/document/reader/website_reader.py
pinaxai/document/reader/youtube_reader.py
pinaxai/document/reader/s3/__init__.py
pinaxai/document/reader/s3/pdf_reader.py
pinaxai/document/reader/s3/text_reader.py
pinaxai/embedder/__init__.py
pinaxai/embedder/aws_bedrock.py
pinaxai/embedder/azure_openai.py
pinaxai/embedder/base.py
pinaxai/embedder/cohere.py
pinaxai/embedder/fastembed.py
pinaxai/embedder/fireworks.py
pinaxai/embedder/google.py
pinaxai-1.0.1.dist-info/licenses/LICENSE
pinaxai-1.0.1.dist-info/METADATA
pinaxai-1.0.1.dist-info/WHEEL
pinaxai-1.0.1.dist-info/entry_points.txt
pinaxai-1.0.1.dist-info/top_level.txt
pinaxai-1.0.1.dist-info/RECORD
