Metadata-Version: 2.4
Name: pinaxai
Version: 1.0.1
Summary: Pinaxai: a lightweight library for building Reasoning Agents
Author-email: Greg Fitzgerald <Greg.Fitzgerald@pinax.tech>
License: Copyright (c) Pinaxai, Inc.
Project-URL: homepage, https://pinax.tech
Project-URL: documentation, https://docs.pinax.tech
Keywords: agent,reasoning,llm,large-language-model,framework
Classifier: Development Status :: 5 - Production/Stable
Classifier: Intended Audience :: Developers
Classifier: License :: OSI Approved :: Mozilla Public License 2.0 (MPL 2.0)
Classifier: Programming Language :: Python :: 3
Classifier: Programming Language :: Python :: 3.7
Classifier: Programming Language :: Python :: 3.8
Classifier: Programming Language :: Python :: 3.9
Classifier: Programming Language :: Python :: 3.10
Classifier: Programming Language :: Python :: 3.11
Classifier: Programming Language :: Python :: 3.12
Classifier: Operating System :: OS Independent
Classifier: Topic :: Scientific/Engineering :: Artificial Intelligence
Requires-Python: <4,>=3.7
License-File: LICENSE
Requires-Dist: docstring-parser
Requires-Dist: gitpython
Requires-Dist: httpx
Requires-Dist: pydantic-settings
Requires-Dist: pydantic
Requires-Dist: python-dotenv
Requires-Dist: python-multipart
Requires-Dist: pyyaml
Requires-Dist: rich
Requires-Dist: tomli
Requires-Dist: typer
Requires-Dist: typing-extensions
Provides-Extra: dev
Requires-Dist: mypy; extra == "dev"
Requires-Dist: pytest; extra == "dev"
Requires-Dist: pytest-asyncio; extra == "dev"
Requires-Dist: pytest-cov; extra == "dev"
Requires-Dist: pytest-mock; extra == "dev"
Requires-Dist: ruff; extra == "dev"
Requires-Dist: timeout-decorator; extra == "dev"
Requires-Dist: types-pyyaml; extra == "dev"
Requires-Dist: types-aiofiles; extra == "dev"
Requires-Dist: fastapi; extra == "dev"
Requires-Dist: uvicorn; extra == "dev"
Requires-Dist: arxiv; extra == "dev"
Provides-Extra: azure
Requires-Dist: azure-ai-inference; extra == "azure"
Requires-Dist: aiohttp; extra == "azure"
Provides-Extra: anthropic
Requires-Dist: anthropic; extra == "anthropic"
Provides-Extra: cohere
Requires-Dist: cohere; extra == "cohere"
Provides-Extra: google
Requires-Dist: google-genai; extra == "google"
Provides-Extra: groq
Requires-Dist: groq; extra == "groq"
Provides-Extra: mistral
Requires-Dist: mistralai; extra == "mistral"
Provides-Extra: openai
Requires-Dist: openai; extra == "openai"
Provides-Extra: ollama
Requires-Dist: ollama; extra == "ollama"
Provides-Extra: ibm
Requires-Dist: ibm-watsonx-ai; extra == "ibm"
Provides-Extra: lmstudio
Requires-Dist: lmstudio; extra == "lmstudio"
Provides-Extra: litellm
Requires-Dist: litellm; extra == "litellm"
Provides-Extra: meta
Requires-Dist: llama-api-client; extra == "meta"
Provides-Extra: cerebras
Requires-Dist: cerebras-cloud-sdk; extra == "cerebras"
Provides-Extra: apify
Requires-Dist: apify-client; extra == "apify"
Provides-Extra: cartesia
Requires-Dist: cartesia; extra == "cartesia"
Provides-Extra: exa
Requires-Dist: exa_py; extra == "exa"
Provides-Extra: yfinance
Requires-Dist: yfinance; extra == "yfinance"
Provides-Extra: ddg
Requires-Dist: duckduckgo-search; extra == "ddg"
Provides-Extra: duckdb
Requires-Dist: duckdb; extra == "duckdb"
Provides-Extra: newspaper
Requires-Dist: newspaper4k; extra == "newspaper"
Requires-Dist: lxml_html_clean; extra == "newspaper"
Provides-Extra: youtube
Requires-Dist: youtube_transcript_api; extra == "youtube"
Provides-Extra: firecrawl
Requires-Dist: firecrawl-py; extra == "firecrawl"
Provides-Extra: github
Requires-Dist: PyGithub; extra == "github"
Provides-Extra: gmail
Requires-Dist: google-api-python-client; extra == "gmail"
Requires-Dist: google-auth-httplib2; extra == "gmail"
Requires-Dist: google-auth-oauthlib; extra == "gmail"
Provides-Extra: googlemaps
Requires-Dist: googlemaps; extra == "googlemaps"
Requires-Dist: google-maps-places; extra == "googlemaps"
Provides-Extra: todoist
Requires-Dist: todoist-api-python; extra == "todoist"
Provides-Extra: elevenlabs
Requires-Dist: elevenlabs; extra == "elevenlabs"
Provides-Extra: fal
Requires-Dist: fal_client; extra == "fal"
Provides-Extra: webex
Requires-Dist: webexpythonsdk; extra == "webex"
Provides-Extra: mcp
Requires-Dist: mcp; extra == "mcp"
Provides-Extra: browserbase
Requires-Dist: browserbase; extra == "browserbase"
Requires-Dist: playwright; extra == "browserbase"
Provides-Extra: agentql
Requires-Dist: agentql; extra == "agentql"
Provides-Extra: confluence
Requires-Dist: atlassian-python-api; extra == "confluence"
Provides-Extra: zep
Requires-Dist: zep-cloud; extra == "zep"
Provides-Extra: sql
Requires-Dist: sqlalchemy; extra == "sql"
Provides-Extra: postgres
Requires-Dist: psycopg-binary; extra == "postgres"
Requires-Dist: psycopg; extra == "postgres"
Provides-Extra: sqlite
Requires-Dist: sqlalchemy; extra == "sqlite"
Provides-Extra: gcs
Requires-Dist: google-cloud-storage; extra == "gcs"
Provides-Extra: redis
Requires-Dist: redis; extra == "redis"
Provides-Extra: pgvector
Requires-Dist: pgvector; extra == "pgvector"
Provides-Extra: chromadb
Requires-Dist: chromadb; extra == "chromadb"
Provides-Extra: lancedb
Requires-Dist: lancedb==0.20.0; extra == "lancedb"
Requires-Dist: tantivy; extra == "lancedb"
Provides-Extra: qdrant
Requires-Dist: qdrant-client; extra == "qdrant"
Provides-Extra: cassandra
Requires-Dist: cassio; extra == "cassandra"
Provides-Extra: mongodb
Requires-Dist: pymongo[srv]; extra == "mongodb"
Provides-Extra: singlestore
Requires-Dist: sqlalchemy; extra == "singlestore"
Provides-Extra: weaviate
Requires-Dist: weaviate-client; extra == "weaviate"
Provides-Extra: milvusdb
Requires-Dist: pymilvus; extra == "milvusdb"
Provides-Extra: clickhouse
Requires-Dist: clickhouse-connect; extra == "clickhouse"
Provides-Extra: pinecone
Requires-Dist: pinecone==5.4.2; extra == "pinecone"
Provides-Extra: pdf
Requires-Dist: pypdf; extra == "pdf"
Requires-Dist: rapidocr_onnxruntime; extra == "pdf"
Provides-Extra: docx
Requires-Dist: python-docx; extra == "docx"
Provides-Extra: text
Requires-Dist: aiofiles; extra == "text"
Provides-Extra: csv
Requires-Dist: aiofiles; extra == "csv"
Provides-Extra: performance
Requires-Dist: memory_profiler; extra == "performance"
Provides-Extra: cookbooks
Requires-Dist: inquirer; extra == "cookbooks"
Requires-Dist: email_validator; extra == "cookbooks"
Provides-Extra: docker
Requires-Dist: pinaxai-docker; extra == "docker"
Provides-Extra: aws
Requires-Dist: pinaxai-aws; extra == "aws"
Provides-Extra: models
Requires-Dist: pinaxai[anthropic]; extra == "models"
Requires-Dist: pinaxai[azure]; extra == "models"
Requires-Dist: pinaxai[cohere]; extra == "models"
Requires-Dist: pinaxai[google]; extra == "models"
Requires-Dist: pinaxai[groq]; extra == "models"
Requires-Dist: pinaxai[mistral]; extra == "models"
Requires-Dist: pinaxai[ollama]; extra == "models"
Requires-Dist: pinaxai[openai]; extra == "models"
Requires-Dist: pinaxai[ibm]; extra == "models"
Requires-Dist: pinaxai[litellm]; extra == "models"
Requires-Dist: pinaxai[meta]; extra == "models"
Requires-Dist: pinaxai[cerebras]; extra == "models"
Provides-Extra: tools
Requires-Dist: pinaxai[apify]; extra == "tools"
Requires-Dist: pinaxai[exa]; extra == "tools"
Requires-Dist: pinaxai[cartesia]; extra == "tools"
Requires-Dist: pinaxai[ddg]; extra == "tools"
Requires-Dist: pinaxai[duckdb]; extra == "tools"
Requires-Dist: pinaxai[newspaper]; extra == "tools"
Requires-Dist: pinaxai[youtube]; extra == "tools"
Requires-Dist: pinaxai[firecrawl]; extra == "tools"
Requires-Dist: pinaxai[github]; extra == "tools"
Requires-Dist: pinaxai[gmail]; extra == "tools"
Requires-Dist: pinaxai[googlemaps]; extra == "tools"
Requires-Dist: pinaxai[todoist]; extra == "tools"
Requires-Dist: pinaxai[elevenlabs]; extra == "tools"
Requires-Dist: pinaxai[fal]; extra == "tools"
Requires-Dist: pinaxai[webex]; extra == "tools"
Requires-Dist: pinaxai[mcp]; extra == "tools"
Requires-Dist: pinaxai[browserbase]; extra == "tools"
Requires-Dist: pinaxai[agentql]; extra == "tools"
Requires-Dist: pinaxai[confluence]; extra == "tools"
Requires-Dist: pinaxai[zep]; extra == "tools"
Provides-Extra: storage
Requires-Dist: pinaxai[sql]; extra == "storage"
Requires-Dist: pinaxai[postgres]; extra == "storage"
Requires-Dist: pinaxai[sqlite]; extra == "storage"
Requires-Dist: pinaxai[gcs]; extra == "storage"
Requires-Dist: pinaxai[redis]; extra == "storage"
Provides-Extra: vectordbs
Requires-Dist: pinaxai[pgvector]; extra == "vectordbs"
Requires-Dist: pinaxai[chromadb]; extra == "vectordbs"
Requires-Dist: pinaxai[lancedb]; extra == "vectordbs"
Requires-Dist: pinaxai[qdrant]; extra == "vectordbs"
Requires-Dist: pinaxai[cassandra]; extra == "vectordbs"
Requires-Dist: pinaxai[mongodb]; extra == "vectordbs"
Requires-Dist: pinaxai[singlestore]; extra == "vectordbs"
Requires-Dist: pinaxai[weaviate]; extra == "vectordbs"
Requires-Dist: pinaxai[milvusdb]; extra == "vectordbs"
Requires-Dist: pinaxai[clickhouse]; extra == "vectordbs"
Requires-Dist: pinaxai[pinecone]; extra == "vectordbs"
Provides-Extra: knowledge
Requires-Dist: pinaxai[pdf]; extra == "knowledge"
Requires-Dist: pinaxai[docx]; extra == "knowledge"
Requires-Dist: pinaxai[text]; extra == "knowledge"
Requires-Dist: pinaxai[csv]; extra == "knowledge"
Provides-Extra: tests
Requires-Dist: pinaxai[dev]; extra == "tests"
Requires-Dist: pinaxai[models]; extra == "tests"
Requires-Dist: pinaxai[tools]; extra == "tests"
Requires-Dist: pinaxai[storage]; extra == "tests"
Requires-Dist: pinaxai[vectordbs]; extra == "tests"
Requires-Dist: pinaxai[knowledge]; extra == "tests"
Requires-Dist: pinaxai[performance]; extra == "tests"
Requires-Dist: pinaxai[cookbooks]; extra == "tests"
Requires-Dist: boto3; extra == "tests"
Requires-Dist: yfinance; extra == "tests"
Requires-Dist: twine; extra == "tests"
Requires-Dist: build; extra == "tests"
Dynamic: license-file
